ewha_anomaly_dynamicP/__init__ .py
ewha_anomaly_dynamicP/anomaly_dynamicP.py
ewha_anomaly_dynamicp-0.1.1.dist-info/METADATA
ewha_anomaly_dynamicp-0.1.1.dist-info/WHEEL
ewha_anomaly_dynamicp-0.1.1.dist-info/top_level.txt
ewha_anomaly_dynamicp-0.1.1.dist-info/RECORD
